{"live":[{"id":"4JQj_deuia8","channelId":"UCRWF6QSuklmwY3UJHyVTQ1w","title":"【Gartic Phone】Drawing with members!! (I suck at drawing)【PRISM Project Gen 1】","status":"live","viewers":49,"published":1669227347,"scheduled":1669253400,"start":1669253502}],"upcoming":[{"id":"5Mj51VSVx7E","channelId":"UCBJFsaCvgBa1a9BnEaxu97Q","title":"RKNGL Radio: Rita's Advice Corner + Special Announcement!","status":"upcoming","viewers":0,"published":1668981663,"scheduled":1669478400,"start":null},{"id":"nW-axX9nTp0","channelId":"UCBJFsaCvgBa1a9BnEaxu97Q","title":"Hanging out with Luto!! ❤【Minecraft】","status":"upcoming","viewers":0,"published":1668981588,"scheduled":1669428000,"start":null},{"id":"lwSROY5MrB0","channelId":"UCBJFsaCvgBa1a9BnEaxu97Q","title":"Recruiting Tali!!【Mass Effect 2】","status":"upcoming","viewers":0,"published":1668981435,"scheduled":1669330800,"start":null},{"id":"xtfER6e7MLw","channelId":"UCswvd6_YWmd6riRk-8oT-sA","title":"【Members tarot】Reading for Shiki Snack tier!!【PRISM Project Gen 3】","status":"upcoming","viewers":0,"published":1668998905,"scheduled":1669586400,"start":null},{"id":"mJvyy4y4FuM","channelId":"UCswvd6_YWmd6riRk-8oT-sA","title":"【Bramble: The Mountain King】Trying the DEMO!!!!【PRISM Project Gen 3】","status":"upcoming","viewers":0,"published":1668998867,"scheduled":1669507200,"start":null},{"id":"pT_WJBbDLfA","channelId":"UCswvd6_YWmd6riRk-8oT-sA","title":"【MEMES】Southern Meme Reading!!【PRISM Project Gen 3】","status":"upcoming","viewers":0,"published":1668998663,"scheduled":1669420800,"start":null},{"id":"UfkL1YgS2YY","channelId":"UCswvd6_YWmd6riRk-8oT-sA","title":"【SOUTHERN SISTER RP】POV: you come home for the holidays【PRISM Project Gen 3】","status":"upcoming","viewers":0,"published":1668998351,"scheduled":1669339800,"start":null},{"id":"HklGYm9I6mk","channelId":"UCswvd6_YWmd6riRk-8oT-sA","title":"【WATCHALONG】Let's watch Man of the House!!【PRISM Project Gen 3】","status":"upcoming","viewers":0,"published":1668997921,"scheduled":1669255200,"start":null},{"id":"AqBNrgMJcEQ","channelId":"UC0ZTVxCHkZanT5dnP2FZD4Q","title":"Gen 3 | Let's draw each other","status":"upcoming","viewers":0,"published":1669025589,"scheduled":1669680000,"start":null},{"id":"u69rr_n4pII","channelId":"UCw1KNjVqfrJSfcFd6zlcSzA","title":"【Call of Duty: MWII】My 100th Date w/ Ghost【PRISM Project Gen 3】","status":"upcoming","viewers":0,"published":1669076777,"scheduled":1669581000,"start":null},{"id":"LRCfcorA25w","channelId":"UCw1KNjVqfrJSfcFd6zlcSzA","title":"【Inside The Backrooms】There's A New Sewer Level!?【PRISM Project Gen 3】","status":"upcoming","viewers":0,"published":1669077353,"scheduled":1669505400,"start":null},{"id":"Em8Js7PFm5c","channelId":"UCw1KNjVqfrJSfcFd6zlcSzA","title":"【Resident Evil 2 Remake】Finally Continuing This Game...【PRISM Project Gen 3】","status":"upcoming","viewers":0,"published":1669077130,"scheduled":1669413600,"start":null},{"id":"9nPqGraPtvU","channelId":"UC2hWFlqMew61Jy6A8zu5HzQ","title":"【Subnautica】Fishies?? Fishies.【PRISM Project】","status":"upcoming","viewers":0,"published":1669132483,"scheduled":1669262400,"start":null},{"id":"rGQ_rah1Hi4","channelId":"UC2hWFlqMew61Jy6A8zu5HzQ","title":"【Fall Guys】with Ikuminship!【PRISM Project】","status":"upcoming","viewers":0,"published":1669133384,"scheduled":1669608000,"start":null},{"id":"8F8BWFKQzMc","channelId":"UC2hWFlqMew61Jy6A8zu5HzQ","title":"【A Little to the Left】I heard there was a cat【PRISM Project】","status":"upcoming","viewers":0,"published":1669133007,"scheduled":1669348800,"start":null},{"id":"z5P1L7YlEUM","channelId":"UCgM1sly6rnxqWe8GLbceEag","title":"【Yakuza 4 Remastered】First time playing a Yakuza game (on stream)!!!","status":"upcoming","viewers":0,"published":1669191190,"scheduled":1669258800,"start":null},{"id":"k-zKujybGcI","channelId":"UC0ZTVxCHkZanT5dnP2FZD4Q","title":"【Pokemon Violet】I am 6 years old","status":"upcoming","viewers":0,"published":1669217769,"scheduled":1669266000,"start":null},{"id":"a8kSxwdnHIk","channelId":"UC0ZTVxCHkZanT5dnP2FZD4Q","title":"【FreeTalk | 雑談】Get ready to travel and pack","status":"upcoming","viewers":0,"published":1669227220,"scheduled":1669294800,"start":null}]}