{"live":[{"id":"pLIZOzUChzs","channelId":"UCBJFsaCvgBa1a9BnEaxu97Q","title":"【Cover】 Chiisana Boukensha | A Little Adventurer 【Rita Kamishiro】","status":"live","viewers":0,"published":1675717208,"scheduled":1675724400,"start":1675717208}],"upcoming":[{"id":"BWw1C0-wGPU","channelId":"UC2hWFlqMew61Jy6A8zu5HzQ","title":"【Album Release Party】CLOUD19 IS OUT!!!【PRISM Project】","status":"upcoming","viewers":0,"published":1676408961,"scheduled":1676780100,"start":null},{"id":"ARLLcr4wisY","channelId":"UC2hWFlqMew61Jy6A8zu5HzQ","title":"【2nd Anniversary Celebration】I have been hiding something...【PRISM Project】","status":"upcoming","viewers":0,"published":1676408815,"scheduled":1676692800,"start":null},{"id":"GY8aQhSVR4w","channelId":"UC2hWFlqMew61Jy6A8zu5HzQ","title":"【Handcam】Trying perler beads for the first time!!【PRISM Project】","status":"upcoming","viewers":0,"published":1676408713,"scheduled":1676606400,"start":null},{"id":"FS6xpKFUUUM","channelId":"UC2hWFlqMew61Jy6A8zu5HzQ","title":"【Original】blue green【Hoshifuri Iku】","status":"upcoming","viewers":0,"published":1675887754,"scheduled":1677384000,"start":null},{"id":"LfzwPhdDh9k","channelId":"UC2hWFlqMew61Jy6A8zu5HzQ","title":"【Original】プリズムのように (PRISM no youni) 【Hoshifuri Iku】","status":"upcoming","viewers":0,"published":1676409032,"scheduled":1676779200,"start":null},{"id":"qmd_WPLwKkA","channelId":"UC0ZTVxCHkZanT5dnP2FZD4Q","title":"【Drinking!】Izakaya looks fun!","status":"upcoming","viewers":0,"published":1676419520,"scheduled":1676725200,"start":null},{"id":"ZqIvAujYv3s","channelId":"UC0ZTVxCHkZanT5dnP2FZD4Q","title":"【Gunpla Building】MG ZGMF-X10A Freedom Gundam","status":"upcoming","viewers":0,"published":1676419351,"scheduled":1676638800,"start":null},{"id":"G9CU0AWmPeg","channelId":"UCx_A6fns9qKjybu-6k0ur1g","title":"D-do I even want to date any of them in 3 hours?...【Speed Dating: Fashioning Little Miss Lonesome】","status":"upcoming","viewers":0,"published":1676418875,"scheduled":1676872800,"start":null},{"id":"GZ_MYGOaobA","channelId":"UCx_A6fns9qKjybu-6k0ur1g","title":"Will we become the ULTIMATE seducer in 3 hours???【Speed Dating: Super Seducer】","status":"upcoming","viewers":0,"published":1676418767,"scheduled":1676786400,"start":null},{"id":"hAagv9Fe-Wo","channelId":"UCx_A6fns9qKjybu-6k0ur1g","title":"Can we get a happy ending with an Alpaca in 3 Hours???【Speed Dating: Paca Plus】","status":"upcoming","viewers":0,"published":1676418582,"scheduled":1676700000,"start":null},{"id":"JqnvO23kE8U","channelId":"UCx_A6fns9qKjybu-6k0ur1g","title":"【Speed Dating: Later Daters】How many grandparents can we date in 3 hours??","status":"upcoming","viewers":0,"published":1676418432,"scheduled":1676613600,"start":null},{"id":"3DNJu3gcqz8","channelId":"UCBJFsaCvgBa1a9BnEaxu97Q","title":"Who's favorite character is the BEST VALENTINE?? 【Oshi Outrage】","status":"upcoming","viewers":0,"published":1676481198,"scheduled":1676847600,"start":null},{"id":"2RRsaqsBCQw","channelId":"UCBJFsaCvgBa1a9BnEaxu97Q","title":"Rachni, Krogan, and Tuchunka!!【Mass Effect 3】","status":"upcoming","viewers":0,"published":1676480574,"scheduled":1676674800,"start":null},{"id":"Fu2PSfVYA2Y","channelId":"UCBJFsaCvgBa1a9BnEaxu97Q","title":"Everything is not how it seems...  【A Space for the Unbound】","status":"upcoming","viewers":0,"published":1676481342,"scheduled":1676732400,"start":null},{"id":"BjpjL32VH7s","channelId":"UCRWF6QSuklmwY3UJHyVTQ1w","title":"【Pokémon Violet】It's time...【PRISM Project Gen 1】","status":"upcoming","viewers":0,"published":1676560157,"scheduled":1676602800,"start":null}]}