{"live":[{"id":"aU_xGtOfrmY","channelId":"UCswvd6_YWmd6riRk-8oT-sA","title":"【AMONG US】BIG PRISM COLLAB!! NOT SUS!!【PRISM Project Gen 3】","status":"live","viewers":52,"published":1697075192,"scheduled":1697245396,"start":1697245545},{"id":"5-QbdGgc8fY","channelId":"UC2hWFlqMew61Jy6A8zu5HzQ","title":"【Among Us】with the PRISM girlies!! 【PRISM Project】","status":"live","viewers":52,"published":1697126376,"scheduled":1697245200,"start":1697245476},{"id":"qHLx_UZOtl4","channelId":"UCJwnGUjoniJA3It-P2snc-A","title":"[AMONG US] first beeg PRISM collab wiff my senpais!! [VTUBER]","status":"live","viewers":0,"published":1697199795,"scheduled":1697245200,"start":null},{"id":"TiQKfR6Lrb4","channelId":"UCkjP_w607B-n4kWJrZAsHMQ","title":"【AMONG US】Sussy Froggy Plays with Cute PRISM Senpais【Ami Amami | PRISM Project Gen 5】","status":"live","viewers":37,"published":1697210765,"scheduled":1697245200,"start":1697245427},{"id":"VTZodl4ETYE","channelId":"UCqVwRGYcVavZ49rGmPB1DKA","title":"【Among Us】prism plays pamongus【PRISM Project Gen 7】","status":"live","viewers":131,"published":1697228018,"scheduled":1697245200,"start":1697245451}],"upcoming":[{"id":"1Z5OB_uvXlU","channelId":"UCswvd6_YWmd6riRk-8oT-sA","title":"【twitter space】im in the bath【PRISM Project Gen 3】","status":"upcoming","viewers":0,"published":1685666302,"scheduled":1748824800,"start":null},{"id":"b4fWELXB-qg","channelId":"UCkjP_w607B-n4kWJrZAsHMQ","title":"AmiAmi Academy Student Lounge","status":"upcoming","viewers":0,"published":1693620292,"scheduled":1748829900,"start":null},{"id":"9qbhn87yTQs","channelId":"UCqVwRGYcVavZ49rGmPB1DKA","title":"【TWITTER SPACE MOMENT】here's ur chat...【PRISM Project Gen 7】","status":"upcoming","viewers":0,"published":1693786940,"scheduled":1725409200,"start":null},{"id":"a0FNmGSo4xA","channelId":"UCkjP_w607B-n4kWJrZAsHMQ","title":"【IDOL TRAINING】Bi-Weekly Karaoke: ???【Ami Amami | PRISM Project Gen 5】","status":"upcoming","viewers":0,"published":1696554764,"scheduled":1697407200,"start":null},{"id":"oaq_sUDxyDU","channelId":"UC2hWFlqMew61Jy6A8zu5HzQ","title":"【Cover】MIRA - Kanaria 【Iku Hoshifuri with @NakiKamizuki @YuraRikudou @LutoAraka 】","status":"upcoming","viewers":0,"published":1696706977,"scheduled":1697859000,"start":null},{"id":"uv-3PJDGnNQ","channelId":"UC2hWFlqMew61Jy6A8zu5HzQ","title":"【Original】PRISM no youni (2.0 version) 【Lost feat. Iku Hoshifuri】","status":"upcoming","viewers":0,"published":1696707699,"scheduled":1698636600,"start":null},{"id":"rj01vnVkyUE","channelId":"UCswvd6_YWmd6riRk-8oT-sA","title":"【ZATSU】OKAY NEXT CHAPTER【PRISM Project Gen 3】","status":"upcoming","viewers":0,"published":1696814756,"scheduled":1697396400,"start":null},{"id":"cgKUjjTdh4U","channelId":"UCswvd6_YWmd6riRk-8oT-sA","title":"【UNARCHIVED KARAOKE】YEEHAW SONGS ONLY【PRISM Project Gen 3】","status":"upcoming","viewers":0,"published":1696814719,"scheduled":1697331600,"start":null},{"id":"0F5gdE_ncPw","channelId":"UCswvd6_YWmd6riRk-8oT-sA","title":"【The Walking Dead】last chapter ended with a bang【PRISM Project Gen 3】","status":"upcoming","viewers":0,"published":1696814447,"scheduled":1697310000,"start":null},{"id":"gtR6EvCFfgM","channelId":"UCx_A6fns9qKjybu-6k0ur1g","title":"I am fine with flunking ;-; Collab w/ Jun, Iku and Xander!【Lunch Lady Collab】","status":"upcoming","viewers":0,"published":1696475721,"scheduled":1697432400,"start":null},{"id":"S2G8GVNMI1g","channelId":"UCx_A6fns9qKjybu-6k0ur1g","title":"【ASMR Kissing (?)】Giving disgusting chus to poop against my will (Calming? But not for me.)","status":"upcoming","viewers":0,"published":1696475468,"scheduled":1697259600,"start":null},{"id":"A5_2pq3mXRI","channelId":"UCx_A6fns9qKjybu-6k0ur1g","title":"僕は依存症 (I am Addicted) / by MikitoP & Eshikara【Iku Hoshifuri & Non Anon Cover】","status":"upcoming","viewers":0,"published":1696587194,"scheduled":1697340600,"start":null},{"id":"sR9vk5kuEws","channelId":"UCx_A6fns9qKjybu-6k0ur1g","title":"【COVER AFTERPARTY】We chatting about the cover & maybe m-minecwaft? w/ @IkuHoshifuri","status":"upcoming","viewers":0,"published":1696690430,"scheduled":1697342400,"start":null},{"id":"obrFhNarDj8","channelId":"UC2hWFlqMew61Jy6A8zu5HzQ","title":"【Luigi's Mansion 3】Wait...let her cook 【PRISM Project】","status":"upcoming","viewers":0,"published":1696934111,"scheduled":1697428800,"start":null},{"id":"iHRumIaRnPw","channelId":"UCC2VYZ_sgiCII711gd6gHnA","title":"i want to go apple picking... 【ZATSUDAN】","status":"upcoming","viewers":0,"published":1696965840,"scheduled":1697292000,"start":null},{"id":"gsfyn35ECZQ","channelId":"UCgM1sly6rnxqWe8GLbceEag","title":"【Mad Father + Jumpscare Alerts】Madness  Runs In The Family~❤❤","status":"upcoming","viewers":0,"published":1697203818,"scheduled":1697252400,"start":null}]}