{"live":[],"upcoming":[{"id":"UCOK2VxY9vc","channelId":"UCkJ64W0J7R0zCSAsZfRIhVQ","title":"[ELDEN RING] Where was I again? [PRISM Project Gen 4]","status":"upcoming","viewers":0,"published":1672629190,"scheduled":1672887600,"start":null},{"id":"F-ZfHVNdtMo","channelId":"UCkJ64W0J7R0zCSAsZfRIhVQ","title":"[LITERATURE MONTH] Judging books by their covers [PRISM Project Gen 4]","status":"upcoming","viewers":0,"published":1672628978,"scheduled":1672801200,"start":null},{"id":"R3Bd7I3rCdM","channelId":"UCkJ64W0J7R0zCSAsZfRIhVQ","title":"[CHOO CHOO CHARLES] Can't sleep, train will eat me [PRISM Project Gen 4]","status":"upcoming","viewers":0,"published":1672628727,"scheduled":1672711200,"start":null},{"id":"SWyZIEnwfVY","channelId":"UCkJ64W0J7R0zCSAsZfRIhVQ","title":"[CRUSADER KINGS III] Building up Bumthang [PRISM Project Gen 4]","status":"upcoming","viewers":0,"published":1672629331,"scheduled":1673042400,"start":null},{"id":"Wr7z4Potzas","channelId":"UCBJFsaCvgBa1a9BnEaxu97Q","title":"Adventure is out there~! Windtrace and more!!【Genshin Impact】","status":"upcoming","viewers":0,"published":1672421567,"scheduled":1672786800,"start":null}]}